{
  "name": "adapt-contrib-assessment",
  "version": "4.5.5",
  "framework": ">=5.8",
  "homepage": "https://github.com/adaptlearning/adapt-contrib-assessment",
  "bugs": "https://github.com/adaptlearning/adapt-contrib-assessment/issues",
  "extension": "assessment",
  "displayName": "Assessment",
  "description": "An extension which attaches to an article object to group various question components and provide a score with feedback",
  "main": "/js/adapt-assessmentArticleExtension.js",
  "keywords": [
    "adapt-plugin",
    "adapt-extension"
  ],
  "license": "GPL-3.0",
  "targetAttribute": "_assessment",
  "_release": "4.5.5",
  "_resolution": {
    "type": "version",
    "tag": "v4.5.5",
    "commit": "b69b03d1cfab3be685ed9a3f78e187abb68b9fb4"
  },
  "_source": "https://github.com/adaptlearning/adapt-contrib-assessment.git",
  "_target": "4.5.5",
  "_originalSource": "adapt-contrib-assessment",
  "_direct": true
}